django_websites/__init__.py
django_websites/apps.py
django_websites/filters.py
django_websites/messages.py
django_websites/options.py
django_websites/permissions.py
django_websites/views.py
django_websites/__pycache__/__init__.cpython-37.pyc
django_websites/__pycache__/apps.cpython-37.pyc
django_websites/__pycache__/filters.cpython-37.pyc
django_websites/__pycache__/messages.cpython-37.pyc
django_websites/__pycache__/options.cpython-37.pyc
django_websites/__pycache__/permissions.cpython-37.pyc
django_websites/__pycache__/views.cpython-37.pyc
django_websites/helpers/__init__.py
django_websites/helpers/button.py
django_websites/helpers/permission.py
django_websites/helpers/siteurl.py
django_websites/helpers/__pycache__/__init__.cpython-37.pyc
django_websites/helpers/__pycache__/button.cpython-37.pyc
django_websites/helpers/__pycache__/permission.cpython-37.pyc
django_websites/helpers/__pycache__/siteurl.cpython-37.pyc
django_websites/templates/sites/base.html
django_websites/templates/sites/create.html
django_websites/templates/sites/delete.html
django_websites/templates/sites/edit.html
django_websites/templates/sites/index.html
django_websites/templates/sites/inspect.html
django_websites/templates/sites/includes/fieldset.html
django_websites/templates/sites/includes/filter.html
django_websites/templates/sites/includes/pagination.html
django_websites/templates/sites/includes/results.html
django_websites/templates/sites/includes/results_row.html
django_websites/templates/sites/shared/messages.html
django_websites/templatetags/__init__.py
django_websites/templatetags/formutils_tags.py
django_websites/templatetags/pagination_tags.py
django_websites/templatetags/__pycache__/__init__.cpython-37.pyc
django_websites/templatetags/__pycache__/formutils_tags.cpython-37.pyc
django_websites/templatetags/__pycache__/pagination_tags.cpython-37.pyc
django_websites/utils/__init__.py
django_websites/utils/datetime.py
django_websites/utils/decorator.py
django_websites/utils/text.py
django_websites-0.0.1.dist-info/LICENSE
django_websites-0.0.1.dist-info/METADATA
django_websites-0.0.1.dist-info/WHEEL
django_websites-0.0.1.dist-info/top_level.txt
django_websites-0.0.1.dist-info/RECORD
